loopHoling/__init__.py
loopHoling/api.py
loopHoling/exp1.py
loopHoling/ml.py
loopHoling/tempCodeRunnerFile.py
loopHoling-0.9.dist-info/METADATA
loopHoling-0.9.dist-info/WHEEL
loopHoling-0.9.dist-info/top_level.txt
loopHoling-0.9.dist-info/RECORD
