Metadata-Version: 2.1
Name: loopHoling
Version: 0.9
Summary: A simple hello world package
Home-page: https://github.com/yourusername/loopHoling
Author: kumar
Author-email: kumar1956.11.1@gmail.com
Classifier: Programming Language :: Python :: 3
Classifier: Operating System :: OS Independent
Requires-Dist: google.generativeai
